odoo/addons/sale_order_discount_fast_change_ui/README.rst
odoo/addons/sale_order_discount_fast_change_ui/__init__.py
odoo/addons/sale_order_discount_fast_change_ui/__manifest__.py
odoo/addons/sale_order_discount_fast_change_ui/i18n/es.po
odoo/addons/sale_order_discount_fast_change_ui/i18n/it.po
odoo/addons/sale_order_discount_fast_change_ui/i18n/sale_order_discount_fast_change_ui.pot
odoo/addons/sale_order_discount_fast_change_ui/readme/CONTRIBUTORS.rst
odoo/addons/sale_order_discount_fast_change_ui/readme/DESCRIPTION.rst
odoo/addons/sale_order_discount_fast_change_ui/readme/USAGE.rst
odoo/addons/sale_order_discount_fast_change_ui/security/ir.model.access.csv
odoo/addons/sale_order_discount_fast_change_ui/static/description/icon.png
odoo/addons/sale_order_discount_fast_change_ui/static/description/index.html
odoo/addons/sale_order_discount_fast_change_ui/static/src/js/sale_order_view.js
odoo/addons/sale_order_discount_fast_change_ui/tests/__init__.py
odoo/addons/sale_order_discount_fast_change_ui/tests/test_sale_order_discount_fast_change.py
odoo/addons/sale_order_discount_fast_change_ui/views/assets.xml
odoo/addons/sale_order_discount_fast_change_ui/views/sale_order_view.xml
odoo/addons/sale_order_discount_fast_change_ui/wizard/__init__.py
odoo/addons/sale_order_discount_fast_change_ui/wizard/sale_order_discount_fast_change.py
odoo/addons/sale_order_discount_fast_change_ui/wizard/sale_order_discount_fast_change.xml
odoo14_addon_sale_order_discount_fast_change_ui-14.0.1.0.2.dev10.dist-info/METADATA
odoo14_addon_sale_order_discount_fast_change_ui-14.0.1.0.2.dev10.dist-info/WHEEL
odoo14_addon_sale_order_discount_fast_change_ui-14.0.1.0.2.dev10.dist-info/top_level.txt
odoo14_addon_sale_order_discount_fast_change_ui-14.0.1.0.2.dev10.dist-info/RECORD
