Metadata-Version: 2.1
Name: odoo14-addon-sale_order_discount_fast_change_ui
Version: 14.0.1.0.2.dev10
Summary: This module disables the slow odoo discount change wizard interface and replaces it with a non transactional faster one
Home-page: https://github.com/OCA/sale-workflow
Author: Akretion, Odoo Community Association (OCA)
Author-email: support@odoo-community.org
License: LGPL-3
Classifier: Programming Language :: Python
Classifier: Framework :: Odoo
Classifier: Framework :: Odoo :: 14.0
Classifier: License :: OSI Approved :: GNU Lesser General Public License v3 (LGPLv3)
Requires-Python: >=3.6
Requires-Dist: odoo<14.1dev,>=14.0a
